Metadata-Version: 2.1
Name: dynamic-heartbeat
Version: 0.0.1
Summary: Dynamic Heartbeat Interval Generator for Python.
Home-page: https://github.com/HoBeedzc
Author: Hobee Liu
Author-email: Hobee.Liu@gmail.com
License: MIT
Keywords: dynamic_heartbeat python
